[{"name": "OPI Gel Color - \"Suzi & The Artic Fox\", 0.5 Fl Oz - Purple", "free_returns": true, "items_sold": null, "price": 900, "status": "New without box", "shipping": 0}, {"name": "Fros\u00e8 Semi Permanent Hair Color 4 oz by Artic Fox", "free_returns": true, "items_sold": null, "price": 1677, "status": "Brand New", "shipping": 592}, {"name": "Arctic Fox Semi Permanent Hair Dye 4 Fl Oz Blue Jean Baby New Sealed", "free_returns": true, "items_sold": null, "price": 1125, "status": "New without box", "shipping": 400}, {"name": "Artic Fox neon moon Semi-Permanent Hair Color 8 Fl. Oz RARE ONLY ONE ON EBAY!", "free_returns": false, "items_sold": null, "price": 1999, "status": "Brand New", "shipping": 900}, {"name": "TY beanie boos-Frost The attic Fox (Walgreens Exclusive) 6 Inch", "free_returns": false, "items_sold": null, "price": 6600, "status": "Brand New", "shipping": 550}, {"name": "Squishmallow Faldette Blue Artic Fox Stuffed Animal Plush Doll Kellytoy 15\u201d Toy", "free_returns": false, "items_sold": null, "price": 2037, "status": "Pre-Owned", "shipping": 0}, {"name": "Arctic Fox Semi Permanent Hair Dye 4 Fl Oz Wrath New Sealed", "free_returns": true, "items_sold": null, "price": 1125, "status": "New without box", "shipping": 400}, {"name": "Arctic Fox Semi Permanent Hair Dye 4 Fl Oz Ritual New Sealed", "free_returns": true, "items_sold": null, "price": 1125, "status": "New without box", "shipping": 400}, {"name": "Arctic Fox Semi Permanent Hair Dye 4 Fl Oz Transylvania Silver New Sealed", "free_returns": true, "items_sold": null, "price": 1125, "status": "New without box", "shipping": 400}, {"name": "ARTIC FOX 'BLEACH, PLEASE Complete Hair Lightening Kit Vegan Cruelty Free", "free_returns": false, "items_sold": null, "price": 2295, "status": "Brand New", "shipping": 0}, {"name": "Artic Fox Color Frose", "free_returns": false, "items_sold": null, "price": 1250, "status": "New without box", "shipping": 560}, {"name": "New ListingCuddlekins artic fox", "free_returns": false, "items_sold": null, "price": 1500, "status": "Pre-Owned", "shipping": 1400}, {"name": "Artic Fox Semi Permanent Hair Color - 8 oz SUNSET ORANGE", "free_returns": false, "items_sold": null, "price": 1300, "status": "New without box", "shipping": 620}, {"name": "LUXURY Artic Marble fox fur Vest Poncho  with Whole skins And  Leather, gift", "free_returns": false, "items_sold": null, "price": 82000, "status": "Brand New", "shipping": 0}, {"name": "Women's bomber jacket with natural fox fur (milk color)", "free_returns": false, "items_sold": null, "price": 33500, "status": "Brand New", "shipping": 0}, {"name": "LUXURY ARTIC Fox fur Jacket/coat with Whole skins, fur jacket,luxury fur,present", "free_returns": false, "items_sold": 0, "price": 289900, "status": "Brand New", "shipping": 0}, {"name": "artic fox periwinkle hair dye", "free_returns": false, "items_sold": null, "price": 1500, "status": "New without box", "shipping": 535}, {"name": "Fros\u00e8 Semi Permanent Hair Color 4 oz by Artic Fox Vegan", "free_returns": true, "items_sold": null, "price": 1999, "status": "New without box", "shipping": 0}, {"name": "Semi Permanent Hair Color Artic Fox  Wrath Bordeaux Furia  8fl", "free_returns": false, "items_sold": null, "price": 1533, "status": "New without box", "shipping": 610}, {"name": "Squishmallow Travel Neck Pillow Melani The Artic Fox Series 1 Rare BNWT", "free_returns": false, "items_sold": null, "price": 1550, "status": "Brand New", "shipping": 1085}, {"name": "Elf Pets Artic Fox", "free_returns": false, "items_sold": 0, "price": 2300, "status": "Brand New", "shipping": 1265}, {"name": "Artic Fox neon moon Semi-Permanent Hair Color 8 Fl. Oz RARE ONLY ONE ON EBAY!", "free_returns": false, "items_sold": null, "price": 2500, "status": "New without box", "shipping": 399}, {"name": "Squishville Six Mini Squishmallows Artic Squad Brand New In Box KellyToy Yeti", "free_returns": false, "items_sold": null, "price": 3600, "status": "Brand New", "shipping": 1125}, {"name": "Squishmallows Gracelynn the Artic Fox 4.5\" Scarf Christmas Holiday Winter NWT   ", "free_returns": false, "items_sold": null, "price": 995, "status": "Brand New", "shipping": 400}, {"name": "Wild Republic White Artic Fox 12\" Plush Stuffed Animal", "free_returns": true, "items_sold": null, "price": 1039, "status": "Pre-Owned", "shipping": 617}, {"name": "Squishmallows 12\u201d Nadine The Artic Fox w/Scarf Christmas Holiday Plush NWT", "free_returns": false, "items_sold": null, "price": 1987, "status": "Brand New", "shipping": 0}, {"name": " White Artic Fox UNIPAK Plush Stuffed Animal New ", "free_returns": true, "items_sold": null, "price": 1299, "status": "Brand New", "shipping": 599}, {"name": "Squishmallow 12\u201d Nadine The Artic Fox Plush Kellytoy New with Tag NWT", "free_returns": false, "items_sold": null, "price": 2699, "status": "Brand New", "shipping": 0}, {"name": "Squishmallow Faldette 16\" Blue Artic Fox Stuffed Animal Plush Doll Kellytoy 2022", "free_returns": false, "items_sold": null, "price": 3595, "status": "Brand New", "shipping": 753}, {"name": "LONG ARTIC Fox fur COAT, with Whole skins, fur jacket,luxury fur,Real fur, gift", "free_returns": false, "items_sold": 0, "price": 430000, "status": "Brand New", "shipping": 0}, {"name": "Artic White Fox Winter Holiday Vintage Aluminium License Plate For Auto ATV Bike", "free_returns": false, "items_sold": null, "price": 1499, "status": "Brand New", "shipping": 0}, {"name": "Douglas Cuddle Toys Porter Artic Fox DLux #2440 Stuffed Animal Toy", "free_returns": false, "items_sold": null, "price": 3495, "status": "Brand New", "shipping": 0}, {"name": "Squishmallow Faldette The Blue Artic Fox Cloudy Tye Dye Plush 2021 12\" NWT", "free_returns": false, "items_sold": null, "price": 1350, "status": "Brand New", "shipping": 610}, {"name": "New ListingWild Republic Artic Fox White 12\u201d Plush Stuffed Animal Toy 12228 New with Tags ", "free_returns": false, "items_sold": null, "price": 599, "status": "Brand New", "shipping": 1260}, {"name": "NWT Real Fur Luxury Women Vest Natural Artic Fox Coat Jacket Black Size Xs/S", "free_returns": false, "items_sold": null, "price": 40000, "status": "New (Other)", "shipping": 1260}, {"name": "Artic fox aquamarine semi- permanent hair color  4 fl oz", "free_returns": false, "items_sold": null, "price": 900, "status": "New without box", "shipping": 1557}, {"name": "ARCTIC ARMY BROWN PARKA BOMBER REAL FOX FUR PARKA HOOD JACKET OVERSIZE UNISEX BN", "free_returns": false, "items_sold": null, "price": 5639, "status": "New (Other)", "shipping": 5497}, {"name": "New ListingSquishmallow 8\u201d Fifi Artic Fox Cuddle Buddy Plush Toy Doll", "free_returns": false, "items_sold": null, "price": 999, "status": "Pre-Owned", "shipping": 1260}, {"name": "RARE Medium Ty Frost The Beanie Boo(Walgreens Exclusive)", "free_returns": false, "items_sold": null, "price": 9550, "status": "Pre-Owned", "shipping": 0}, {"name": "VINTAGE * Joseph J Stefani Furs* White & Brown Womens Soft Artic Fox Fur Coat S", "free_returns": false, "items_sold": null, "price": 99500, "status": "Pre-Owned", "shipping": 1705}, {"name": "NWT Real Fur Luxury Women Vest Natural Artic Fox Coat Jacket Nude Khaki Size S/M", "free_returns": false, "items_sold": null, "price": 40000, "status": "New (Other)", "shipping": 1260}, {"name": "New Kellytoy Squishmallow  8\" FIFI the pink artic fox Plush Toy", "free_returns": false, "items_sold": null, "price": 1599, "status": "Brand New", "shipping": 525}, {"name": "Squishville Six Mini Squishmallows Artic Squad Brand New In Box KellyToy", "free_returns": false, "items_sold": 0, "price": 3199, "status": "Brand New", "shipping": 610}, {"name": "Squishmallows Squishville Artic Squad Nadine the Artic Fox 2\"", "free_returns": false, "items_sold": null, "price": 1095, "status": "Brand New", "shipping": 400}, {"name": "Planet Earth BBC 2006 Rare Artic Fox      EA", "free_returns": false, "items_sold": null, "price": 1999, "status": "Brand New", "shipping": 1190}, {"name": "Squishmallow Faldette 16\" Blue Artic Fox Stuffed Animal Plush Doll Kellytoy 2022", "free_returns": false, "items_sold": null, "price": 2999, "status": "Brand New", "shipping": 798}, {"name": "artic fox frose hair dye 8oz", "free_returns": false, "items_sold": null, "price": 1500, "status": "New without box", "shipping": 660}, {"name": "Squishmallows 12\u201d Nadine The Artic Fox w/Scarf Christmas Holiday Plush NWT", "free_returns": false, "items_sold": null, "price": 2500, "status": "Brand New", "shipping": 1275}, {"name": "Natural Artic Silver Fox Fox Fur Coat GORGEOUS!", "free_returns": false, "items_sold": 0, "price": 165000, "status": "Pre-Owned", "shipping": 5500}, {"name": "NEW, Squishmallow Gracelynn the Artic Fox 4.5\" ", "free_returns": true, "items_sold": null, "price": 1000, "status": "Brand New", "shipping": 400}, {"name": "Squishmallow Heidi Husky Dog Wolf Artic Fox Plush Tie Dyed Gray/White Stuffed 5\"", "free_returns": false, "items_sold": null, "price": 1498, "status": "Brand New", "shipping": 0}, {"name": "Squishmallow Faldette 16\" Blue Artic Fox Stuffed Animal Plush Doll Kellytoy 2021", "free_returns": true, "items_sold": 0, "price": 4299, "status": "Brand New", "shipping": 0}, {"name": "Squishmallow Faldette 16\" Blue Artic Fox Stuffed Animal Plush Doll Kellytoy 2021", "free_returns": false, "items_sold": null, "price": 3999, "status": "Brand New", "shipping": 399}, {"name": "Squishmallow Gracelynn Artic Fox 12\" Soft Plush with Fuzzy Rainbow Belly NWT ", "free_returns": false, "items_sold": null, "price": 2794, "status": "Brand New", "shipping": 600}, {"name": "CHELSEA VIOLET Articfox Faux Fur polar fox  fluffy cloud soft jacker coat M $118", "free_returns": false, "items_sold": null, "price": 6500, "status": "Brand New", "shipping": 1115}, {"name": "LIVING NATURE ARTIC FOX PLUSH 45CM - AN426 TEDDY WHITE FAUX FUR SOFT & CUDDLY", "free_returns": true, "items_sold": null, "price": 2096, "status": "Brand New", "shipping": 1274}, {"name": "Posers Artic White Fox ? Fur Jacket 12 VTG Velvet Lined Pockets Shoulder Pads", "free_returns": false, "items_sold": 0, "price": 41280, "status": "Pre-Owned", "shipping": 2505}, {"name": "Natural White Artic Shadow Fox Fur Coat STUNNING!", "free_returns": false, "items_sold": 0, "price": 115000, "status": "Pre-Owned", "shipping": 5500}, {"name": "New ListingVintage Artic Fox Style Sport Obermeyer Ski Jacket Size 14", "free_returns": false, "items_sold": null, "price": 12000, "status": "Pre-Owned", "shipping": 1710}, {"name": "Squishmallow Gracelynn Artic Fox Soft Plush 12\" White and Rainbow", "free_returns": false, "items_sold": null, "price": 1791, "status": "Pre-Owned", "shipping": 699}, {"name": "Beautiful Oscar de la Renta 3/4 Length Grey Artic Fox Fur Coat with Hood, Small", "free_returns": true, "items_sold": null, "price": 119999, "status": "Pre-Owned", "shipping": 3500}, {"name": "Vtg Alexander White Artic Fox Fur & Black Leather Coat Russian Princess Small", "free_returns": false, "items_sold": 0, "price": 50000, "status": "Pre-Owned", "shipping": 2135}, {"name": "Rare Animal Jam Artic Fox Plush", "free_returns": false, "items_sold": 0, "price": 2998, "status": "Pre-Owned", "shipping": 0}, {"name": "Wild Republic White Artic Fox 12\" Plush Solid White w Grey Feet Winter Display", "free_returns": false, "items_sold": null, "price": 1200, "status": "Pre-Owned", "shipping": 675}, {"name": "Douglas Cuddle Toys Artic Fox White Snow Queen #1893 Stuffed Animal Toy ", "free_returns": false, "items_sold": null, "price": 2200, "status": "Pre-Owned", "shipping": 685}, {"name": "Fiesta 13\" Artic Fox White Fur  Plush Stuffed Animal Kids Toy Unisex Adult", "free_returns": false, "items_sold": null, "price": 2249, "status": "Pre-Owned", "shipping": 700}, {"name": "Fur Vest Real Natural Artic Fox Fur Vest Coat Real Women Jacket Size S", "free_returns": false, "items_sold": null, "price": 35000, "status": "Pre-Owned", "shipping": 2245}, {"name": "Wild Republic 12\u201d Artic Wolf/Fox/Dog Soft Plush White Stuffed Animal Toy", "free_returns": false, "items_sold": null, "price": 749, "status": "Pre-Owned", "shipping": 1115}, {"name": "Ganz Webkinz HM210 Artic Fox Plush - NO Code Stuffed Fluffy Animal", "free_returns": true, "items_sold": null, "price": 1399, "status": "Pre-Owned", "shipping": 0}, {"name": "European Full-Length Genuine Leather w/ Artic Fox Collar, hand Trim Coat & Hat", "free_returns": false, "items_sold": null, "price": 55000, "status": "Pre-Owned", "shipping": 9172}, {"name": "Unipak Artic Fox 12\" Plush Arctic Tag White Canine Stuffed Animal Dog Wolf Toy", "free_returns": false, "items_sold": null, "price": 1500, "status": "Pre-Owned", "shipping": 1260}, {"name": "Artic Fox Korean Made Long Sleeve Jacket Large Acrylic/wool", "free_returns": false, "items_sold": null, "price": 1799, "status": "Pre-Owned", "shipping": 1125}, {"name": "Safari LTD Artic Fox Animal Figure", "free_returns": true, "items_sold": null, "price": 699, "status": "Pre-Owned", "shipping": 560}, {"name": "Fox Pair Cufflinks Silver Vulpes Artic Wedding Fancy Gift Box & Polishing Cloth", "free_returns": true, "items_sold": null, "price": 1699, "status": "Brand New", "shipping": 0}, {"name": "Arctic Bay Down Goose Aurora parka jacket Big  fox fur made Canada  msrp1050$", "free_returns": false, "items_sold": null, "price": 51373, "status": "Brand New", "shipping": 3326}, {"name": "Merrell Boots Womens 7 Artic Fox Pull Waterproof Black Leather Mid Calf Classic", "free_returns": true, "items_sold": null, "price": 4369, "status": "Pre-Owned", "shipping": 1890}, {"name": "Ty Beanie Boos Frost Artic Fox 9\u201d Plush Blue White Toy Walgreens Exclusive Rare", "free_returns": false, "items_sold": null, "price": 17990, "status": "Pre-Owned", "shipping": 685}, {"name": "BUILD A BEAR WILDLIFE SERIES Artic FOX WITH OUTFIT - BOW EUC", "free_returns": false, "items_sold": null, "price": 2250, "status": "Pre-Owned", "shipping": 650}, {"name": "Women's parka with natural fox or bluefrost fur (S,M,L)", "free_returns": false, "items_sold": null, "price": 36500, "status": "Brand New", "shipping": 0}, {"name": "European Full-Length Genuine Leather w/ Artic Fox Collar, hand Trim Coat & Hat", "free_returns": false, "items_sold": null, "price": 55000, "status": "Pre-Owned", "shipping": 9172}, {"name": "Unipak Artic Fox 12\" Plush Arctic Tag White Canine Stuffed Animal Dog Wolf Toy", "free_returns": false, "items_sold": null, "price": 1500, "status": "Pre-Owned", "shipping": 1260}, {"name": "Artic Fox Korean Made Long Sleeve Jacket Large Acrylic/wool", "free_returns": false, "items_sold": null, "price": 1799, "status": "Pre-Owned", "shipping": 1125}, {"name": "Safari LTD Artic Fox Animal Figure", "free_returns": true, "items_sold": null, "price": 699, "status": "Pre-Owned", "shipping": 560}, {"name": "vintage full length artic fox coat small/medium", "free_returns": false, "items_sold": null, "price": 39500, "status": "Pre-Owned", "shipping": 2875}, {"name": "Large Genuine Fox Fur Jacket Artic Silver Valentine Furrier Dallas", "free_returns": false, "items_sold": null, "price": 60000, "status": "Pre-Owned", "shipping": 2245}, {"name": "Squishmallow Gracelynn Artic White Fox 8\" Plush Target Exc| 2020 Kelly Toys EUC", "free_returns": false, "items_sold": null, "price": 1199, "status": "Pre-Owned", "shipping": 455}, {"name": " Full-length Artic Marble Fox Fur Coat Tuxedo Collar Glamorous ", "free_returns": false, "items_sold": null, "price": 600000, "status": "New (Other)", "shipping": 1670}, {"name": "DISCOVERY CHANNEL Akur Soft White Arctic Fox Plush Stuffed Animal ", "free_returns": false, "items_sold": null, "price": 2499, "status": "Pre-Owned", "shipping": 1710}, {"name": "Khaki bomber jacket for women with natural fur of raccoon, bluefrost, arctic fox", "free_returns": false, "items_sold": null, "price": 32000, "status": "Brand New", "shipping": 0}, {"name": "CASE COVER FOR GOOGLE PIXEL|ARTIC FOX 1", "free_returns": false, "items_sold": null, "price": 640, "status": "Brand New", "shipping": 1030}, {"name": "Martha Stewart Mini Molded Glass Ornaments Artic Holiday Rabbit Fox Owl Fox Pola", "free_returns": false, "items_sold": null, "price": 2795, "status": "Brand New", "shipping": 595}, {"name": "ARTIC FOX DENIM WINTER JACKET PARKA", "free_returns": false, "items_sold": null, "price": 26000, "status": "New (Other)", "shipping": 2220}, {"name": "\ud83d\udc9dNEW\ud83d\udc9d 5inch Heidi Husky Dog Wolf Artic Fox Christmas | Brand New | 5\" Gift", "free_returns": false, "items_sold": 0, "price": 1595, "status": "Brand New", "shipping": 0}, {"name": "BUILD A BEAR WILDLIFE SERIES Artic FOX TAN BROWN WITH DENIM SHORTS 3239", "free_returns": true, "items_sold": null, "price": 2377, "status": "Pre-Owned", "shipping": 899}, {"name": "Target Squishmallows White Gracelyn the Arctic Fox Tie Dye Tummy Kellytoy 8\u201d", "free_returns": true, "items_sold": null, "price": 1199, "status": "Pre-Owned", "shipping": 425}, {"name": "National Geographic Kids Stuffed Toy Lot Artic Fox Beluga Whale Bengal Tiger 3\u201d", "free_returns": true, "items_sold": null, "price": 880, "status": "Pre-Owned", "shipping": 450}, {"name": "NEW Squishmallow 12\" FALDETTE blue Artic FOX 2022 Kellytoy CUTE Plush Toy", "free_returns": false, "items_sold": null, "price": 1599, "status": "Brand New", "shipping": 1735}, {"name": "DISCOVERY CHANNEL 29\" Akur Soft White Arctic Fox Stuffed Plush Animal ", "free_returns": false, "items_sold": null, "price": 4999, "status": "Pre-Owned", "shipping": 1292}, {"name": "2018 NATL GEOGRAPHIC KIDS MINIATURE ARCTIC FOX PLUSH (MA857)", "free_returns": false, "items_sold": null, "price": 899, "status": "Pre-Owned", "shipping": 0}, {"name": "New  Squishmallow Gracelynn the Artic Fox 4.5\" ", "free_returns": false, "items_sold": null, "price": 1499, "status": "Brand New", "shipping": 610}, {"name": "Unipak Artic Fox 12\" Plush 2011 with Tag White Canine Brown Ears Stuffed Animal", "free_returns": false, "items_sold": null, "price": 2140, "status": "Pre-Owned", "shipping": 0}, {"name": "Realistic Plush White Artic Fox Discovery Channel 16\" Tall Stuffed Animal HTF", "free_returns": false, "items_sold": null, "price": 1725, "status": "Pre-Owned", "shipping": 7630}, {"name": "Jakks Pacific Animal Babies ARTIC FOX Doll 16\" Vinyl Stuffed Plush Baby Sound ", "free_returns": false, "items_sold": null, "price": 4500, "status": "Pre-Owned", "shipping": 0}, {"name": "Artic Fox by John James Audubon Vintage Illustration Art Poster 20x30", "free_returns": false, "items_sold": null, "price": 999, "status": null, "shipping": 695}, {"name": "Women's New Balance 860 V11 Artic Fox Running Shoe  *SIZE 8.5B ONLY    *W860W11", "free_returns": false, "items_sold": 0, "price": 8999, "status": "New (Other)", "shipping": 0}, {"name": "Women's New Balance 880 V11 Artic Fox (White) Running Shoe *W880A11", "free_returns": false, "items_sold": 0, "price": 8999, "status": "New (Other)", "shipping": 0}, {"name": "New Balance Womens W520rz3 Artic Fox/Black Running Shoes Size 5 (1864642)", "free_returns": true, "items_sold": null, "price": 3849, "status": "New (Other)", "shipping": 0}, {"name": "RETRO 90S OFF WHITE REAL RABBIT FUR REAL ARTIC FOX COLLAR OVERLAP JACKET sz M", "free_returns": false, "items_sold": null, "price": 8900, "status": "Pre-Owned", "shipping": 950}, {"name": "Unipak Artic Fox 12\" Plush White Wolf Canine Stuffed Animal Dog Toy Lovey Puppy", "free_returns": false, "items_sold": null, "price": 995, "status": "Pre-Owned", "shipping": 600}, {"name": "Wild Republic White Artic Fox 12\u201d Stuffed Plush Animal w/Tags NEW  ", "free_returns": false, "items_sold": null, "price": 1888, "status": "Brand New", "shipping": 2220}, {"name": "Overlook Bay \u2606 Artic Fox x4", "free_returns": false, "items_sold": null, "price": 399, "status": "Pre-Owned", "shipping": null}, {"name": "Squishville Six Mini Squishmallows Artic Squad", "free_returns": false, "items_sold": 0, "price": 2895, "status": "Brand New", "shipping": 685}, {"name": "Vintage Natural Artic Silver Fox Fox Fur Coat  - Weinstocks Fine Furs Sxz s - lg", "free_returns": false, "items_sold": null, "price": 50000, "status": "Pre-Owned", "shipping": 2000}, {"name": "Fur hat real silver fox and mink women's winter classic", "free_returns": true, "items_sold": null, "price": 26500, "status": "Brand New", "shipping": 800}, {"name": "5stars full skin Artic Fox  FUR throw,fur comforter,fox fur blanket,fur rug ", "free_returns": false, "items_sold": 0, "price": 245000, "status": "Brand New", "shipping": 0}, {"name": "Wild Republic Artic Fox White 12\u201d Plush Stuffed Animal Toy 12228 New with Tags ", "free_returns": false, "items_sold": null, "price": 1999, "status": "Brand New", "shipping": 795}, {"name": "Wild Republic Detroit Zoo Artic Fox White 12\" Plush Stuffed Animal", "free_returns": false, "items_sold": null, "price": 1484, "status": "Pre-Owned", "shipping": 0}, {"name": "Fiesta Arctic Fox Realistic Plush Toy Stuffed Animal 13\" vintage", "free_returns": false, "items_sold": null, "price": 4995, "status": "Pre-Owned", "shipping": 0}, {"name": "2018 National Geographic Kids Artic Fox Miniature Stuffed Toy", "free_returns": false, "items_sold": null, "price": 1150, "status": "Pre-Owned", "shipping": 660}, {"name": "Arctic Fox Trim Parka Size S", "free_returns": false, "items_sold": null, "price": 69900, "status": "Brand New", "shipping": 2245}, {"name": "WILD REPUBLIC WHITE ARTIC FOX 12\" PLUSH VERY SOFT & FLUFFY STUFFED ANIMAL", "free_returns": false, "items_sold": null, "price": 1495, "status": "Pre-Owned", "shipping": 695}, {"name": "Bear Surprise By Just Play Panda Bear Plush w/Her 2 Adopted Artic Fox Babies 14\"", "free_returns": false, "items_sold": null, "price": 2123, "status": "Pre-Owned", "shipping": 0}, {"name": "Squishmallows Nadine The Artic Fox Plush Christmas Holiday 2021 Scarf Kellytoys", "free_returns": false, "items_sold": null, "price": 2800, "status": "Brand New", "shipping": 1575}, {"name": "Squishmallows FALDETTE Blue Artic Fox 11\" Stuffed Plush - New with Tags", "free_returns": false, "items_sold": null, "price": 1999, "status": "Brand New", "shipping": 1325}, {"name": "Artic Fox Snow White Vintage Tack Pin T-393", "free_returns": true, "items_sold": null, "price": 999, "status": "Pre-Owned", "shipping": 450}, {"name": "DISCOVERY CHANNEL Soft White Arctic Fox Stuffed Plush Animal ", "free_returns": false, "items_sold": null, "price": 8500, "status": "Pre-Owned", "shipping": 0}, {"name": "LUXURY ARTIC Fox fur Jacket/coat with Whole skins, fur jacket,luxury fur,present", "free_returns": false, "items_sold": null, "price": 200000, "status": "Pre-Owned", "shipping": null}, {"name": "SQUISHMALLOWS  Kellytoy 16\" \"RIENNE\" GREEN ARTIC FOX Stuffed Animal With Tag", "free_returns": false, "items_sold": null, "price": 3500, "status": "Pre-Owned", "shipping": 1200}, {"name": "Wild Republic - CK Lil's - Artic Fox - 5\"", "free_returns": false, "items_sold": null, "price": 950, "status": "Brand New", "shipping": 660}, {"name": "Ratermann Artic Fox 60\" Stainless Steel Cryogenic Flex Hose cleaned for oxygen", "free_returns": false, "items_sold": null, "price": 7999, "status": "Brand New", "shipping": 1169}, {"name": "Squishmallow Faldette 16\" Blue Artic Fox Stuffed Animal Plush Doll Kellytoy 2021", "free_returns": false, "items_sold": null, "price": 3000, "status": "Brand New", "shipping": 1470}, {"name": "Squishmallow, Blue Artic Fox Melani Squishmallow Plush Doll, 8\" KellyToy NWT", "free_returns": false, "items_sold": null, "price": 3500, "status": "Brand New", "shipping": 495}, {"name": "Women's winter bomber jacket with real fox fur", "free_returns": false, "items_sold": null, "price": 34500, "status": "Brand New", "shipping": 0}, {"name": "Squishmallow FALDETTE the FOX 12\" plush Artic BLUE tie-dye soft squishy pillow", "free_returns": false, "items_sold": null, "price": 1999, "status": "Brand New", "shipping": 940}, {"name": "Vtg Mint 50's Leonard Furs Animal Silver Artic Fox Fur Stripe Coat Jacket", "free_returns": false, "items_sold": null, "price": 199999, "status": "Pre-Owned", "shipping": 0}, {"name": "RARE 2014 Squishable 7\" Blue Arctic Fox Plush + Justice Undercover Unicorn Mask ", "free_returns": false, "items_sold": null, "price": 6998, "status": "Pre-Owned", "shipping": 900}, {"name": "Faldette The Artic Fox Sky Blue 12\" Squishmallow Plush Toy by Kelly Toy NWT", "free_returns": false, "items_sold": null, "price": 2499, "status": "Brand New", "shipping": 1099}, {"name": "NWT UNIPAK White Artic Fox Wolf Stuffed Plush", "free_returns": false, "items_sold": null, "price": 2499, "status": "Brand New", "shipping": 1710}, {"name": "ARTIC FOX Antique Cigar Box Label T Shirt SMALL-XXXLARGE (F)", "free_returns": false, "items_sold": null, "price": 1399, "status": "Brand New", "shipping": 500}, {"name": "Squishmallows 12\u201d Nadine The Artic Fox w/Scarf Christmas Holiday Plush NWT", "free_returns": false, "items_sold": null, "price": 1500, "status": "Brand New", "shipping": 540}, {"name": "Wild Republic 12\u201d Artic Fox Wolf Plush Soft White Stuffed Animal", "free_returns": false, "items_sold": null, "price": 1249, "status": "Pre-Owned", "shipping": 1260}, {"name": "Worthington Wm L Dupont ThermoliteTM Insulation Fox Fur Removbl Hood Plum Parka ", "free_returns": false, "items_sold": null, "price": 4899, "status": "Pre-Owned", "shipping": 2220}, {"name": "Ratermann Artic Fox 36\" Stainless Steel Cryogenic Flex Hose cleaned for oxygen", "free_returns": false, "items_sold": null, "price": 5999, "status": "Brand New", "shipping": 1169}, {"name": "Beautiful Ranch Blue Artic Fox Pelt Fresh Tanned Fur USA Quality Furs   3 Feet", "free_returns": false, "items_sold": null, "price": 11000, "status": "Brand New", "shipping": 1260}, {"name": "Squishmallows Kellytoy 12\u201d Faldette The Blue Artic Fox Exclusive Stuffed Plush", "free_returns": false, "items_sold": null, "price": 2500, "status": "Brand New", "shipping": 610}, {"name": "Elf on the Shelf, Elf Pets - ARTIC FOX, Storybook Included - New in Box", "free_returns": false, "items_sold": null, "price": 3150, "status": "Brand New", "shipping": 1346}, {"name": "Squishmallows 12\u201d Nadine The Artic Fox w/Scarf Christmas Holiday Plush NWT", "free_returns": false, "items_sold": null, "price": 4500, "status": "Brand New", "shipping": 1710}, {"name": "Zippo Artic Fox#28272", "free_returns": false, "items_sold": null, "price": 2000, "status": "Brand New", "shipping": 500}, {"name": "Vintage Women's FUR Stroller Coat DEL RUBIO ESTATE Fox?", "free_returns": false, "items_sold": null, "price": 30485, "status": null, "shipping": 0}, {"name": "Webkinz ARTIC FOX Plush Toy Doll HM210 NWT + Sealed code!", "free_returns": false, "items_sold": null, "price": 4950, "status": "Brand New", "shipping": 685}, {"name": "Dolly Fox Comin' On Strong 45 RPM Single Record Artic Records 1978 AR 1-D78 Y", "free_returns": true, "items_sold": null, "price": 629, "status": "Pre-Owned", "shipping": 425}, {"name": "OPI Powder Perfection - Pick Your Color - Save When You Buy More!", "free_returns": false, "items_sold": null, "price": 1395, "status": "New without box", "shipping": 0}, {"name": "Wonders Of The Animal Kingdom Mini Info Paper Of The Artic Fox #61", "free_returns": true, "items_sold": null, "price": 501, "status": "Pre-Owned", "shipping": 500}, {"name": "Fur hat real arctik fox women's winter classic", "free_returns": true, "items_sold": null, "price": 13500, "status": "Brand New", "shipping": 800}, {"name": "White & Grey FOX Synthetic Artic FUR So Soft Jacket S 12 Excellent Condition", "free_returns": false, "items_sold": null, "price": 4061, "status": "Pre-Owned", "shipping": 2605}, {"name": "VXN-8 Artic Fox yr 1981 H4368 35mm Aircraft Slide", "free_returns": false, "items_sold": null, "price": 112, "status": "Pre-Owned", "shipping": 316}, {"name": "Rare Squishmallows Travel Neck Pillow Melani The Artic Fox Series 1 NEW Tags", "free_returns": false, "items_sold": null, "price": 2695, "status": "Brand New", "shipping": 1575}, {"name": "Pam Schifferl White Santa With Artic Fox & Rabbit Christmas Figurine Rare Figure", "free_returns": true, "items_sold": null, "price": 4800, "status": "Pre-Owned", "shipping": 585}, {"name": "SAN DIEGO ZOO ARTIC FOX Elongated Pressed Smashed Penny 10", "free_returns": false, "items_sold": null, "price": 229, "status": null, "shipping": 0}, {"name": "Beautiful Ranch Blue Artic Fox Pelt Fresh Tanned Fur USA Quality Furs  3 Feet", "free_returns": false, "items_sold": null, "price": 11000, "status": "Brand New", "shipping": 1260}, {"name": "Hallmark Northpole Snowby Polar Bear & Flitter Artic Fox Plush Ornaments", "free_returns": true, "items_sold": null, "price": 1295, "status": "Brand New", "shipping": 0}, {"name": "Parka with fox or silver fox fur along the edge of the hood", "free_returns": false, "items_sold": null, "price": 30000, "status": "Brand New", "shipping": 0}, {"name": "Wiebe Wicked Sharp Artic Fox Folding Scalpel Knife Survivalist  trap traps trapp", "free_returns": false, "items_sold": 0, "price": 3495, "status": "Brand New", "shipping": 655}, {"name": "New Balance Womens W520rz3 Artic Fox/Black Running Shoes Size 5 (1421265)", "free_returns": true, "items_sold": null, "price": 3849, "status": "New (Other)", "shipping": 0}, {"name": "Animal Jam Crystal Artic Fox Purple Palace Den Vinyl 3\" Figure Figurine", "free_returns": false, "items_sold": null, "price": 524, "status": "Pre-Owned", "shipping": 610}, {"name": "Vintage Artic Fox Fur Fluffy Tapered Collar Wrap Stole 53\" Long", "free_returns": false, "items_sold": null, "price": 8499, "status": null, "shipping": 550}, {"name": "wild republic white wolf / Artic Fox plush", "free_returns": false, "items_sold": null, "price": 1257, "status": "Pre-Owned", "shipping": 2070}, {"name": "Hallmark Ornament 2003 Cool Decade White Artic Fox with Redbird #4  ", "free_returns": true, "items_sold": null, "price": 400, "status": "Pre-Owned", "shipping": 427}, {"name": "hallmark 1994 Merry Minitures artic white fox", "free_returns": false, "items_sold": null, "price": 99, "status": "Pre-Owned", "shipping": 600}, {"name": "WEBKINZ Artic Fox HM210 With Gift Bag by Ganz Plush-Beanbag Animal Toy w Tags", "free_returns": false, "items_sold": null, "price": 2000, "status": "Pre-Owned", "shipping": 1710}, {"name": "Ladies Tu Grey Artic Fox Slinky Soft Pyjamas Size 18 BNIP", "free_returns": false, "items_sold": null, "price": 1578, "status": "Brand New", "shipping": 2202}, {"name": "LEGO Minecraft Animals & Minifigures Fox Pig Cow Mooshroom Spider Hal Hex Pirate", "free_returns": true, "items_sold": null, "price": 189, "status": "Brand New", "shipping": 509}, {"name": "LARGE ARTIC FOX STATUE (11\u201d x 13.5\u201d)", "free_returns": false, "items_sold": null, "price": 4000, "status": "Pre-Owned", "shipping": 1645}, {"name": "Safari Artic Fox Figure", "free_returns": false, "items_sold": null, "price": 799, "status": "Pre-Owned", "shipping": 500}, {"name": " HARELINE ARTIC FOX TAIL - Fly Tying", "free_returns": false, "items_sold": null, "price": 582, "status": "Brand New", "shipping": 425}, {"name": "Squishmallow Kellytoy Gracelynn Cat Rainbow Belly, NWT N007 Winter Fox Artic 7\"", "free_returns": false, "items_sold": null, "price": 1995, "status": "Brand New", "shipping": 455}, {"name": "Vintage ARTIC FOX Earrings MADE IN U.S.A.  The Alchemists Copper & Brass", "free_returns": true, "items_sold": null, "price": 1995, "status": "Pre-Owned", "shipping": 0}, {"name": "Artic Fox #4 D&D Icons Of The Realms Icewind Dale Rime Of Frostmaiden", "free_returns": true, "items_sold": null, "price": 440, "status": "Pre-Owned", "shipping": 0}, {"name": "1810 John Wilkes Antique Print of a Artic Fox, Jerboa, Grey Fox & Jackal", "free_returns": false, "items_sold": null, "price": 5499, "status": null, "shipping": 0}, {"name": "NEW West Elm Rachel Kozlowski Dapper Animal Chritmas Artic Fox 8.5\" Salad Plate", "free_returns": false, "items_sold": 0, "price": 1497, "status": "Brand New", "shipping": 1710}, {"name": "Luxury full skin REAL FOX FUR throw,fur comforter,fur blanket,various colors", "free_returns": false, "items_sold": 0, "price": 265000, "status": "Brand New", "shipping": 0}, {"name": "Original Old Antique Print Artic Fox Foxes Quadruped Audubon Color", "free_returns": false, "items_sold": null, "price": 1692, "status": "Pre-Owned", "shipping": 1235}, {"name": "Vintage Alaskan Caribou Skin Mask w/artic fox, beaver, seal by Lilly Killbear", "free_returns": false, "items_sold": null, "price": 5900, "status": null, "shipping": 1190}, {"name": "Zoobles Chillville Collection & Happitat Artic Fox Misty #161", "free_returns": false, "items_sold": null, "price": 999, "status": "Pre-Owned", "shipping": 475}, {"name": "Animal Jam Crystal Palace Den Artic Fox Walmart Exclusive Sealed - NEW", "free_returns": false, "items_sold": null, "price": 3900, "status": "Brand New", "shipping": 1710}, {"name": "ARTIC FOX CENTRAL PARK ZOO Elongated Pressed Smashed Penny 11", "free_returns": false, "items_sold": null, "price": 225, "status": null, "shipping": 0}, {"name": "2003 Hallmark Ornament- Cool Decade 4th in the Series- Artic Fox", "free_returns": false, "items_sold": null, "price": 800, "status": "New (Other)", "shipping": 675}, {"name": "New Balance Womens 520RZ3 Running Shoes, SZ 5.0 WIDE, Artic Fox/Black, NEW 15174", "free_returns": true, "items_sold": 0, "price": 2350, "status": "New (Other)", "shipping": 0}, {"name": "FAUX FUR ARTIC SILVER FOX DARK GREY PREMIUM FABRIC160cm wide MADE IN ITALY D221", "free_returns": true, "items_sold": null, "price": 1117, "status": "Brand New", "shipping": 2106}, {"name": "Webkinz ARTIC FOX Plush Toy Doll HM210 NWT + code NEW", "free_returns": false, "items_sold": null, "price": 7999, "status": "Brand New", "shipping": 1260}, {"name": "Walmart Exclusive New Animal Jam Crystal Palace Den Artic Fox MIB Never Opened", "free_returns": false, "items_sold": null, "price": 5000, "status": "Brand New", "shipping": 1200}, {"name": "New Listing1-ARTIC CAT 600 SX/XC SNO PRO REAR FOX 2.0 RC-2 SHOCK PART #952-03-016", "free_returns": false, "items_sold": null, "price": 49999, "status": "New (Other)", "shipping": 0}, {"name": "Artic Fox Hair  - COMBINED SHIPPING IN CART", "free_returns": true, "items_sold": null, "price": 496, "status": "Brand New", "shipping": 449}, {"name": "69 (Tex 70) Lt-Mid Weight Bonded Nylon/Poly Upholstery Leather Thread (16oz)", "free_returns": false, "items_sold": null, "price": 2000, "status": "Brand New", "shipping": 0}, {"name": "Safari Artic Fox & White Tiger Cub Animals Figures Lot", "free_returns": true, "items_sold": null, "price": 1198, "status": "Pre-Owned", "shipping": 0}, {"name": "Ratermann Artic Fox 48\" Stainless Steel Cryogenic Flex Hose cleaned for oxygen", "free_returns": false, "items_sold": null, "price": 6999, "status": "Brand New", "shipping": 1169}, {"name": "Sleeping White Artic Fox Porcelain Trinket Box", "free_returns": false, "items_sold": null, "price": 2000, "status": "Pre-Owned", "shipping": 1275}, {"name": "New Balance x Isaac Mizrahi Live! Mesh Lace-Up Sneakers 499Q Artic Fox", "free_returns": false, "items_sold": null, "price": 3499, "status": "Brand New", "shipping": 0}, {"name": "Arctic Fox Sportsmans Sharpening Puck", "free_returns": true, "items_sold": null, "price": 2195, "status": "Brand New", "shipping": 0}, {"name": "Fox Stencil Coyote Artic Animal Wild Predator Rustic Cabin Lodge DIY Craft Signs", "free_returns": false, "items_sold": null, "price": 1195, "status": "Brand New", "shipping": 0}, {"name": "IGT AVP Artic Fox Game Install Package", "free_returns": false, "items_sold": null, "price": 7500, "status": "Pre-Owned", "shipping": 0}, {"name": "1-2022 ARTIC CAT ZR 6000 SX FRONT LEFT SKI SHOCK FOX EVOL 0 MILES #3703-949", "free_returns": false, "items_sold": null, "price": 39900, "status": "New (Other)", "shipping": 0}, {"name": "Squishmallows Nadine the Artic Fox w/ Ear Muffs 12\" Australian Exclusive NEW", "free_returns": false, "items_sold": 0, "price": 5148, "status": "Brand New", "shipping": 2433}, {"name": "Fox, Artic, Polar, Very Nice Plastic Toy Animal,    3\"    CWG119 B237", "free_returns": true, "items_sold": null, "price": 379, "status": "Brand New", "shipping": 653}, {"name": "WILLIAMS-SONOMA HOME FAUX FUR THROW - ARTIC FOX", "free_returns": false, "items_sold": null, "price": 17900, "status": "Brand New", "shipping": 1295}, {"name": "VINTAGE ARTIC FOX  CROSS STITCH PATTERN ONLY    #964", "free_returns": false, "items_sold": null, "price": 745, "status": "Pre-Owned", "shipping": 0}, {"name": "Veniard Artic Fox Tail (piece)", "free_returns": false, "items_sold": null, "price": 632, "status": "Brand New", "shipping": 479}, {"name": "ARTIC FOX CENTRAL PARK ZOO COPPER Elongated Pressed Smashed Penny 29", "free_returns": false, "items_sold": null, "price": 225, "status": null, "shipping": 0}, {"name": "2014 CANADA ARTIC FOX .9999 SILVER ROUND", "free_returns": false, "items_sold": null, "price": 4988, "status": null, "shipping": 800}, {"name": "The Elf on the Shelf RARE - ARTIC FOX Plushee Pals MINI Clip-on 4\" ", "free_returns": false, "items_sold": null, "price": 1999, "status": "Brand New", "shipping": 299}, {"name": "POP Artic Fox Not Faux Fur Snap Wrap COLOR CHOICE", "free_returns": false, "items_sold": null, "price": 1200, "status": "Brand New", "shipping": 600}, {"name": "Mini Artic Fox Plush National Geographic Happy Meal 2018 K5.3", "free_returns": false, "items_sold": null, "price": 200, "status": "Pre-Owned", "shipping": 599}, {"name": "Ty FROST Beanie Boos Artic Fox MEDIUM 9\" Walgreens Exclusive MWMT's ", "free_returns": false, "items_sold": null, "price": 19995, "status": "Brand New", "shipping": 495}, {"name": "3 Lot Children's Books Chanda A. Bell: Elf Pets Artic Fox Saint Bernard Reindeer", "free_returns": false, "items_sold": null, "price": 1650, "status": "New (Other)", "shipping": 500}, {"name": "CHRISTMAS Santa Claus Artic Fox Rabbit Reindeer Moon Greeting Card - W/ TRACKING", "free_returns": false, "items_sold": null, "price": 495, "status": "Brand New", "shipping": 359}, {"name": "Canada - 2014 $25.00 Silver O'Canada Artic Fox Coin - No Box", "free_returns": false, "items_sold": null, "price": 3622, "status": null, "shipping": 739}, {"name": "John A. Ruthven \"Artic Fox\" Limited Edition Numbered - 161/950 - Signed", "free_returns": false, "items_sold": null, "price": 21869, "status": null, "shipping": 2046}, {"name": "BYX Co Arctic Fox Sportsmans Puck Medium & Fine Grit Knife Sharpener Stone XAFSP", "free_returns": true, "items_sold": 45, "price": 1948, "status": "Brand New", "shipping": 0}, {"name": "NEW FREE PEOPLE ARTIC FOX BACK ZIP PULLOVER SWEATER SIZE XS Z274-5", "free_returns": true, "items_sold": null, "price": 6240, "status": "New (Other)", "shipping": 800}, {"name": "br71 Blue Artic Fox Taxidermy Oddities Curiosity display specimen collectible", "free_returns": false, "items_sold": null, "price": 59999, "status": "Brand New", "shipping": 15950}, {"name": "OPI Infinite Shine 2 Suzi & The Artic Fox 0.5oz", "free_returns": false, "items_sold": null, "price": 1050, "status": "New without box", "shipping": 0}, {"name": "OPI Suzi & The Artic Fox, Black Dress Not Optional, Rub A Pub Pub ", "free_returns": false, "items_sold": null, "price": 2299, "status": "New without box", "shipping": 399}, {"name": "Ganz Webkinz Artic Fox Plush No Code HM210 Stuffed Animal Floppy Bean Bag Toy 8\"", "free_returns": true, "items_sold": null, "price": 699, "status": "Pre-Owned", "shipping": 599}, {"name": "Hansa Artic Synthetic Fiber Arctic Fox Seated With Multi-Color 3252", "free_returns": false, "items_sold": null, "price": 6175, "status": "Brand New", "shipping": 0}, {"name": "Arctic White Fox scarf bandana pink blue eyes 22\" square wildlife airbrush artic", "free_returns": false, "items_sold": null, "price": 1293, "status": "Pre-Owned", "shipping": 725}, {"name": "Sterling Silver 3D 14x14mm Grey Gray Artic Red Fox Wolf Coyote Charm", "free_returns": false, "items_sold": null, "price": 1899, "status": "New (Other)", "shipping": 535}, {"name": "SCANDINAVIAN full skin Artic Fox  FUR throw,comforter,fox fur blanket,fur rug", "free_returns": false, "items_sold": 0, "price": 146000, "status": "Brand New", "shipping": 0}, {"name": "Sterling Silver 3D 13x16mm Grey Gray Artic Red Fox Wolf Charm", "free_returns": false, "items_sold": 0, "price": 1899, "status": "New (Other)", "shipping": 535}, {"name": "GANZ WEBKINZ Arctic Fox Stuffed Animal Plush Toy 13\"", "free_returns": false, "items_sold": null, "price": 1700, "status": "Pre-Owned", "shipping": 585}, {"name": "BYX Co Artic Fox Dual Sportsmans Puck Gray/Blue Medium Grit Knife Sharpener AFSP", "free_returns": true, "items_sold": null, "price": 2157, "status": "Brand New", "shipping": 0}, {"name": "Vintage Adolf Realites Artic Fox Fur Hat Paris New York Womens 21\u201d", "free_returns": false, "items_sold": null, "price": 8500, "status": "Pre-Owned", "shipping": 850}, {"name": "BESWICK Ceramic Artic Babies - ARTIC FOX CUB  - New 2013", "free_returns": false, "items_sold": null, "price": 2256, "status": "Brand New", "shipping": 4519}, {"name": "Minecraft Dungeons -Artic Fox Armor 100% Flea x 4 Cooldown Xbox/PS4/Switch/PC", "free_returns": false, "items_sold": 0, "price": 1600, "status": "Brand New \u00b7 Sony PlayStation 4 \u00b7 Minecraft", "shipping": 0}, {"name": "MEXA White Artic Fox PAPAKHA Real Genuine Fur Russian WINTER HAT", "free_returns": false, "items_sold": 0, "price": 38999, "status": "Brand New", "shipping": 1115}, {"name": "Artic Fox Women\u2019s Synthetic Wig", "free_returns": false, "items_sold": null, "price": 7500, "status": "Pre-Owned", "shipping": 699}, {"name": "Fox, Artic, Museum Quality Rubber Replica, Hand Painted 3\" CWG205 BB42", "free_returns": false, "items_sold": null, "price": 789, "status": "Brand New", "shipping": 750}, {"name": "3 Lot Children's Books Chanda A. Bell: Elf Pets Artic Fox Saint Bernard Reindeer", "free_returns": false, "items_sold": null, "price": 1500, "status": "Pre-Owned", "shipping": 500}, {"name": "USPS Artic Animals 15 .33 cent US postage stamps Polar Bear Gray Wolf Fox", "free_returns": false, "items_sold": null, "price": 600, "status": null, "shipping": 530}, {"name": "Artic Fox 11/230 Minecraft Card PANINI 2020 Trading", "free_returns": false, "items_sold": null, "price": 150, "status": "Pre-Owned", "shipping": 225}, {"name": "PartyLite Tealight Holder Artic Fox and Kit P93334 Nature's Wonders Animals", "free_returns": false, "items_sold": null, "price": 2999, "status": "New (Other)", "shipping": 1418}, {"name": "NEW Elf Pets An Arctic Fox Tradition Plush & Storybook Elf On The Shelf NEW!", "free_returns": false, "items_sold": null, "price": 6699, "status": "Brand New", "shipping": 0}, {"name": "Authentic Littlest Pet Shop Artic Fox # 1028 Winter Snow Fun Playset Lot Set ", "free_returns": false, "items_sold": null, "price": 2500, "status": "Pre-Owned", "shipping": 480}, {"name": "Dungeons & Dragons Icewind Dale Artic Fox 4/45", "free_returns": false, "items_sold": null, "price": 299, "status": "Pre-Owned", "shipping": 400}, {"name": "WIEBE RED FOX FOLDING SCALPEL BLADE 24 EXTRA BLADES TRAPPING SKINNING  HAVALON ", "free_returns": true, "items_sold": 25, "price": 4175, "status": "Brand New", "shipping": 0}, {"name": "Royal Grafton Artic Fox Cubs Bradex Collector Plate #A3634", "free_returns": false, "items_sold": null, "price": 2998, "status": "Pre-Owned", "shipping": 0}, {"name": "NWT-10\u201d Aurora Artic Fox Plush Animal Dog Husky Solid White Thick Tail Furry", "free_returns": false, "items_sold": null, "price": 1800, "status": "Brand New", "shipping": 660}, {"name": "New Balance Women's WRT300DB Shoes Artic Fox/White Size 9", "free_returns": false, "items_sold": null, "price": 2999, "status": "Pre-Owned", "shipping": 0}, {"name": "(10i) FDC 3289 Artic Fox - DGW", "free_returns": false, "items_sold": null, "price": 375, "status": null, "shipping": 0}, {"name": "ARTIC FOX Money Hunny Repair Serum 2oz Vegan Cruelty Free", "free_returns": false, "items_sold": null, "price": 1800, "status": "New without box", "shipping": 375}, {"name": "Retired 2018 McDonalds Happy Meal Toy National Geographic Kids #3 Artic Fox NIP", "free_returns": true, "items_sold": null, "price": 399, "status": "Pre-Owned", "shipping": 450}, {"name": "NEW artic fox cryogenic hose 3/8\u201d id x 6\u2019 72\u201d Stainless cold frozen ", "free_returns": false, "items_sold": null, "price": 5855, "status": "New \u2013 Open box", "shipping": 1255}, {"name": "NOS Vintage Rupp Bonanza Artic Cat Ruttman Fox Mini Bike Cherry 7/8 Brake Lever", "free_returns": false, "items_sold": null, "price": 1799, "status": "New (Other)", "shipping": 0}, {"name": "Silver Artic Fox Tail Dyed Black (By Foxy Tails) For Fly Tying ** 2022 Stocks **", "free_returns": false, "items_sold": null, "price": 1014, "status": "Brand New", "shipping": 446}, {"name": "Restoration Hardware Luxe Artic Faux Fur Wine Bag Gift Bag Leather Tie NWT", "free_returns": false, "items_sold": null, "price": 2399, "status": "Brand New", "shipping": 545}, {"name": "Chip & Pepper Size 30 Flare Artic Fox Dark Blue Stretch Denim Womens Jeans", "free_returns": true, "items_sold": null, "price": 1206, "status": "Pre-Owned", "shipping": 849}, {"name": "Fox Stencil Red Artic Animal Dog Track Wild Predator Rustic Cabin DIY Craft Sign", "free_returns": false, "items_sold": null, "price": 1395, "status": "Brand New", "shipping": 0}, {"name": "United States #3288-3292 MNH 1999 Arctic Animals Owl Bear Wolf Fox Hare", "free_returns": true, "items_sold": null, "price": 499, "status": null, "shipping": 199}, {"name": "New ListingNew Elf Pets An Arctic Fox Tradition Plush & Storybook Elf On The Shelf NIB ", "free_returns": false, "items_sold": null, "price": 3700, "status": "Brand New", "shipping": 1250}, {"name": "Vintage Postcard 1907-1915 NY Zoological Park Artic Fox Bronx Zoo NY", "free_returns": false, "items_sold": null, "price": 295, "status": "Pre-Owned", "shipping": 295}, {"name": "Ty Beanie Boos 2017 FROST The Artic Fox 6\" Walgreen's Exclusive RARE mint wmtags", "free_returns": false, "items_sold": null, "price": 19999, "status": "Brand New", "shipping": 0}, {"name": "Ganz Webkinz Artic Fox Plush No Code HM210 Blush Pink Knitted Sweater", "free_returns": true, "items_sold": null, "price": 1998, "status": "Pre-Owned", "shipping": 599}, {"name": "Crazy Mountain Snowman & Sleigh with Artic Fox  Tea Light Holder 2001 JLC 529", "free_returns": false, "items_sold": null, "price": 1000, "status": "Pre-Owned", "shipping": 1125}, {"name": "Arctic Fox Round Saddle Fuel Tank Heater", "free_returns": false, "items_sold": 0, "price": 15000, "status": "Pre-Owned", "shipping": 3230}, {"name": "Hansa Artic Synthetic Fiber Fox Arcticwhite 4069", "free_returns": false, "items_sold": null, "price": 7144, "status": "Brand New", "shipping": 0}, {"name": "King Size full skin WHITE  Fox FUR throw,18 Fox Skins,fox fur blanket,fur rug", "free_returns": false, "items_sold": null, "price": 455000, "status": "Brand New", "shipping": 0}, {"name": "New Balance Womens W520rz3 Artic Fox/Black Running Shoes Size 7", "free_returns": false, "items_sold": null, "price": 1199, "status": "Pre-Owned", "shipping": 1710}, {"name": " West Elm Christmas Holiday Plate Rachel Kozlowski Dapper Animals artic fox ", "free_returns": false, "items_sold": null, "price": 2959, "status": "Brand New", "shipping": 999}, {"name": "New Balance \"520v3\" Artic Fox/Black Running Shoes. Women's 6 D (36.5 EUR)", "free_returns": false, "items_sold": 0, "price": 4999, "status": "Brand New", "shipping": 0}, {"name": "*LIMITED TIME SALE ROBLOXBREAKING POINT CHEAP \u2705DIVINE ARCTICS READ DESCRIPTION\u203c\ufe0f", "free_returns": false, "items_sold": null, "price": 295, "status": "Brand New", "shipping": 0}, {"name": "CHRISTMAS Santa Claus Owl Polar Bears Artic Fox Rabbit GLITTERED Greeting Card ", "free_returns": false, "items_sold": null, "price": 459, "status": "Brand New", "shipping": 359}, {"name": "Artic Fox Heaters Hat, Trucker Baseball Cap VTG Vintage", "free_returns": false, "items_sold": null, "price": 695, "status": "Pre-Owned", "shipping": 398}, {"name": "New balance Artic Fox Women 8.5", "free_returns": false, "items_sold": null, "price": 2500, "status": "Pre-Owned", "shipping": 0}, {"name": "CHRISTMAS TRADITION ELF ON THE SHELF PLUSHEE PALS BOY GIRL ARTIC FOX MINI KEY", "free_returns": false, "items_sold": null, "price": 4200, "status": "Brand New", "shipping": 0}, {"name": "Pam Schifferl Winter's Eve Santa w/Artic Fox & Rabbit Christmas Figurine (RARE)", "free_returns": false, "items_sold": null, "price": 7499, "status": "Pre-Owned", "shipping": 495}, {"name": "2013 $20 PCGS PR70DCAM - Untamed Canada - Artic Fox", "free_returns": false, "items_sold": null, "price": 13000, "status": null, "shipping": 560}, {"name": "2018 MCDONALDS RARE ARTIC FOX #3 National Geographic Happy Meal Toy ", "free_returns": false, "items_sold": null, "price": 299, "status": "Pre-Owned", "shipping": 495}, {"name": "Artic Fox Gold Stamp", "free_returns": false, "items_sold": null, "price": 1540, "status": null, "shipping": 0}, {"name": "2 Pack-Reversible Cloth Sanitary Face Mask by Artic Fox Reusable Washable Grey", "free_returns": false, "items_sold": null, "price": 790, "status": "Brand New", "shipping": 0}, {"name": "Hallmark Ornament 2003 Cool Decade White Artic Fox with Redbird #4 REPAINT NEW", "free_returns": true, "items_sold": null, "price": 1395, "status": "Brand New", "shipping": 427}, {"name": "NOS Vintage Rupp Bonanza Artic Cat Ruttman Fox Mini Bike Cherry 7/8 Brake Lever", "free_returns": false, "items_sold": 0, "price": 1799, "status": "New (Other)", "shipping": 0}, {"name": "Gymboree 6-12 mo Artic Fox Gray Romper Back Tail NWT2017", "free_returns": false, "items_sold": null, "price": 2234, "status": "Brand New", "shipping": 590}, {"name": "2000 Alaska Mint The Seal of the State 1 oz .999 Fine Silver Round Artic Fox", "free_returns": false, "items_sold": null, "price": 7995, "status": null, "shipping": 425}, {"name": "Animal~Alaskan Artic Fox on Snowbank~Midnight Sun Twilight~Continental Postcard", "free_returns": true, "items_sold": null, "price": 175, "status": "Pre-Owned", "shipping": 150}, {"name": "Merrell Vibram Waterproof Zipper Boots Womens Size 7 Artic Fox Pull Black", "free_returns": false, "items_sold": null, "price": 4499, "status": "Pre-Owned", "shipping": 2220}, {"name": "2 McDonalds 2018 Happy Meal Toy National Geographic Sloth Bear #9 & Artic Fox #3", "free_returns": false, "items_sold": null, "price": 1099, "status": "Brand New", "shipping": 535}, {"name": "New Balance x Isaac Mizrahi Artic Fox Silver Mesh Lace-Up 499Q Sneakers New", "free_returns": false, "items_sold": 0, "price": 3495, "status": "Brand New", "shipping": 695}, {"name": "BYX Co Artic Fox Dual Sportsmans Puck Gray/Blue Medium Grit Knife Sharpener", "free_returns": true, "items_sold": null, "price": 2282, "status": "Brand New", "shipping": 0}, {"name": "2014 Canadian Artic Fox 9999- 1 1/2 Oz.silver coin", "free_returns": false, "items_sold": null, "price": 7300, "status": null, "shipping": 490}, {"name": "Columbus Zoo & Aquarium Elongated Pennies - Brown Bear, Artic Fox & Owl", "free_returns": false, "items_sold": null, "price": 700, "status": null, "shipping": 0}, {"name": "Artic Fox Hairapy Gummies Vitamins for healthier hair and nails,  NEW, ex. 8/23", "free_returns": false, "items_sold": null, "price": 1500, "status": "Brand New", "shipping": 685}, {"name": "Merrell Artic Fox 6 Snow Hiking Boot Silver Birch Wms Sz 7.5 Waterproof Nubuck", "free_returns": false, "items_sold": null, "price": 4599, "status": "Pre-Owned", "shipping": 1200}, {"name": "Schleich Artic Animal figurines: Artic Fox and Kit, Polar Bear and Cub...", "free_returns": false, "items_sold": null, "price": 3500, "status": "Pre-Owned", "shipping": 1190}, {"name": "Lot of 2 OPI Infinite Shine 2 Suzi & The Artic Fox 0.5oz", "free_returns": false, "items_sold": null, "price": 1500, "status": "New without box", "shipping": 0}, {"name": "2 McDonalds 2018 Happy Meal National Geographic Kids Red Panda #5 & Artic Fox #3", "free_returns": false, "items_sold": null, "price": 1099, "status": "Pre-Owned", "shipping": 535}, {"name": "Elf Pets Arctic Fox Tradition Plush & Storybook Elf On The Shelf & Fox Cub DVD!", "free_returns": true, "items_sold": null, "price": 4999, "status": "New (Other)", "shipping": 0}, {"name": "1990 Polar Expedition Maruri Arctic Fox Fine Porcelain P-9002 Figurine FREE SHIP", "free_returns": false, "items_sold": null, "price": 2599, "status": "Pre-Owned", "shipping": 0}, {"name": "The Artic Fox, Francis Leopold McClinton, David Murphy", "free_returns": false, "items_sold": null, "price": 1128, "status": "Pre-Owned", "shipping": 2493}, {"name": "2013 Canada $20 Artic Fox Untamed Fine Silver Proof #18341", "free_returns": false, "items_sold": null, "price": 5174, "status": null, "shipping": 1774}, {"name": "New York Lake Placid Artic Wolves Silver Fox Farms 1930s Postcard 22-3736", "free_returns": true, "items_sold": null, "price": 914, "status": "Pre-Owned", "shipping": 0}, {"name": "Ganz Webkinz Artic Fox White Plush 8\" No Code Stuffed Animal Toy", "free_returns": true, "items_sold": null, "price": 4799, "status": "Pre-Owned", "shipping": 399}]